<?xml version="1.0" encoding="UTF-8"?>
<objects serializationModel="Studio.02.02.00">
	<object class="AudioFile" id="{8efbf2b9-92aa-4c78-9a92-cc7984828e56}">
		<property name="assetPath">
			<value>char/Footsteps/244267-Footstep_Single_Concrete_Soldier_Run_N02.wav</value>
		</property>
		<property name="frequencyInKHz">
			<value>96</value>
		</property>
		<property name="channelCount">
			<value>2</value>
		</property>
		<property name="length">
			<value>0.54986458333333332</value>
		</property>
		<relationship name="masterAssetFolder">
			<destination>{ba3b4f9d-0349-4463-a323-61f98f1e992c}</destination>
		</relationship>
	</object>
</objects>
